kaparoo_lightning/__about__.py
kaparoo_lightning/__init__.py
kaparoo_lightning/py.typed
kaparoo_lightning/common/__init__.py
kaparoo_lightning/common/types.py
kaparoo_lightning/data/__init__.py
kaparoo_lightning/data/constants.py
kaparoo_lightning/data/datamodules.py
kaparoo_lightning/data/datasets.py
kaparoo_lightning/data/utils.py
kaparoo_lightning/nn/__init__.py
kaparoo_lightning/nn/gan.py
kaparoo_lightning_package-0.2.1.dist-info/METADATA
kaparoo_lightning_package-0.2.1.dist-info/WHEEL
kaparoo_lightning_package-0.2.1.dist-info/licenses/LICENSE
kaparoo_lightning_package-0.2.1.dist-info/RECORD
